pynmranalysis/__init__.py
pynmranalysis/analysis.py
pynmranalysis/normalization.py
pynmranalysis/preprocessing.py
pynmranalysis-1.1.3.dist-info/METADATA
pynmranalysis-1.1.3.dist-info/WHEEL
pynmranalysis-1.1.3.dist-info/license.txt
pynmranalysis-1.1.3.dist-info/top_level.txt
pynmranalysis-1.1.3.dist-info/RECORD
