Metadata-Version: 2.1
Name: pynmranalysis
Version: 1.1.3
Summary: python library for NMR preprocessing and analysis
Home-page: https://github.com/1feres1/pynmranalysis/
Author: Feres Sakouhi
Author-email: feressakouhi@gmail.com
License: MIT
Platform: UNKNOWN
Classifier: Intended Audience :: Science/Research
Classifier: Intended Audience :: Developers
Classifier: Programming Language :: Python :: 3
Classifier: Programming Language :: Python :: 3.6
Classifier: Programming Language :: Python :: 3.7
Classifier: Programming Language :: Python :: 3.8
Classifier: Programming Language :: Python :: 3.9
Classifier: Topic :: Scientific/Engineering
Classifier: Operating System :: MacOS :: MacOS X
Classifier: Operating System :: Microsoft :: Windows
Classifier: Operating System :: POSIX :: Linux
License-File: license.txt
Requires-Dist: numpy
Requires-Dist: pandas (==1.2.4)
Requires-Dist: scipy
Requires-Dist: scikit-learn
Requires-Dist: matplotlib
